{
    "1" :["Boat Quay", "Chinatown", "Havelock Road", "Marina Square", "Raffles Place", "Suntec City", "mbs","suntec","lavender"],
    "2" :["Anson Road", "Chinatown", "Neil Road", "Raffles Place", "Shenton Way", "Tanjong Pagar"],
    "3" :["Alexandra Road", "Tiong Bahru", "Queenstown","redhill"],
    "4" :["Keppel", "Mount Faber", "Sentosa", "Telok Blangah", "vivo", "vivocity","rws","uss"],
    "5" :["Buona Vista", "Dover", "Pasir Panjang", "West Coast","nus"],
    "6" :["City Hall", "High Street", "North Bridge Road", "clarke quay","clark quay", "liang court", "novotel","zouk","smu"],
    "7" :["Beach Road", "Bencoolen Road", "Bugis", "Rochor","prinsep","golden mile"],
    "8" :["Little India", "Farrer Park", "Serangoon Road", "mustafa","swee choon"],
    "9" :["Cairnhill", "Killiney", "Leonie Hill", "Orchard", "Oxley", "cuppage","scape","plaza sing","somerset","concorde","cineleisure","the cathay","robertson"],
    "10":["Balmoral", "Bukit Timah", "Grange Road", "Holland", "Orchard Boulevard", "River Valley", "Tanglin Road"],
    "11":["Chancery", "Bukit Timah", "Dunearn Road", "Newton"],
    "12":["Balestier", "Moulmein", "Novena", "Toa Payoh", "tpy","boon keng"],
    "13":["Potong Pasir", "Macpherson"],
    "14":["Eunos", "Geylang", "Kembangan", "Paya Lebar", "ubi","kaki bukit"],
    "15":["Katong", "Marine Parade", "Siglap", "Tanjong Rhu"],
    "16":["Bayshore", "Bedok", "Chai Chee"],
    "17":["Changi", "Loyang", "jewel"],
    "18":["Pasir Ris", "Simei", "Tampines","tamp","temasek poly"],
    "19":["Hougang", "Punggol", "Sengkang", "Serangoon","kovan","nex","seng kang"],
    "20":["Ang Mo Kio", "amk", "Bishan", "Braddell Road", "Thomson"],
    "21":["Clementi", "Upper Bukit Timah", "Hume Avenue","sim","beauty world"],
    "22":["Boon Lay", "Jurong","Jurong East","Jurong West", "Tuas", "ntu","boonlay","imm","jcube","jem"],
    "23":["Bukit Batok", "bukit panjang", "Choa Chu Kang", "cck", "Hillview Avenue", "Upper Bukit Timah","Yew Tee","yewtee","keat hong","hillview","bukit gombak","teck whye"],
    "24":["Kranji", "Lim Chu Kang", "Sungei Gedong", "Tengah"],
    "25":["Admiralty", "Woodlands","republic poly","marsiling","ngee ann poly"],
    "26":["Tagore", "Yio Chu Kang"],
    "27":["Admiralty", "Sembawang", "Yishun","khatib","orto"],
    "28":["Seletar", "Yio Chu Kang"]
}